freqtrade/__init__.py
freqtrade/__main__.py
freqtrade/constants.py
freqtrade/freqtradebot.py
freqtrade/loggers.py
freqtrade/main.py
freqtrade/misc.py
freqtrade/persistence.py
freqtrade/state.py
freqtrade/utils.py
freqtrade/wallets.py
freqtrade/worker.py
freqtrade/configuration/__init__.py
freqtrade/configuration/arguments.py
freqtrade/configuration/check_exchange.py
freqtrade/configuration/cli_options.py
freqtrade/configuration/config_validation.py
freqtrade/configuration/configuration.py
freqtrade/configuration/deprecated_settings.py
freqtrade/configuration/directory_operations.py
freqtrade/configuration/load_config.py
freqtrade/configuration/timerange.py
freqtrade/data/__init__.py
freqtrade/data/btanalysis.py
freqtrade/data/converter.py
freqtrade/data/dataprovider.py
freqtrade/data/history.py
freqtrade/edge/__init__.py
freqtrade/exchange/__init__.py
freqtrade/exchange/bibox.py
freqtrade/exchange/binance.py
freqtrade/exchange/common.py
freqtrade/exchange/exchange.py
freqtrade/exchange/kraken.py
freqtrade/optimize/__init__.py
freqtrade/optimize/backtesting.py
freqtrade/optimize/default_hyperopt.py
freqtrade/optimize/default_hyperopt_loss.py
freqtrade/optimize/edge_cli.py
freqtrade/optimize/hyperopt.py
freqtrade/optimize/hyperopt_interface.py
freqtrade/optimize/hyperopt_loss_interface.py
freqtrade/optimize/hyperopt_loss_onlyprofit.py
freqtrade/optimize/hyperopt_loss_sharpe.py
freqtrade/pairlist/IPairList.py
freqtrade/pairlist/PrecisionFilter.py
freqtrade/pairlist/PriceFilter.py
freqtrade/pairlist/StaticPairList.py
freqtrade/pairlist/VolumePairList.py
freqtrade/pairlist/__init__.py
freqtrade/pairlist/pairlistmanager.py
freqtrade/plot/__init__.py
freqtrade/plot/plot_utils.py
freqtrade/plot/plotting.py
freqtrade/resolvers/__init__.py
freqtrade/resolvers/exchange_resolver.py
freqtrade/resolvers/hyperopt_resolver.py
freqtrade/resolvers/iresolver.py
freqtrade/resolvers/pairlist_resolver.py
freqtrade/resolvers/strategy_resolver.py
freqtrade/rpc/__init__.py
freqtrade_pro-1.1.6.dist-info/LICENSE
freqtrade_pro-1.1.6.dist-info/METADATA
freqtrade_pro-1.1.6.dist-info/WHEEL
freqtrade_pro-1.1.6.dist-info/top_level.txt
freqtrade_pro-1.1.6.dist-info/RECORD
